example_package/__init__.py
example_package/example.py
addOneSample_bharadwaj-0.0.1.dist-info/LICENSE
addOneSample_bharadwaj-0.0.1.dist-info/METADATA
addOneSample_bharadwaj-0.0.1.dist-info/WHEEL
addOneSample_bharadwaj-0.0.1.dist-info/top_level.txt
addOneSample_bharadwaj-0.0.1.dist-info/RECORD
