Metadata-Version: 2.1
Name: addOneSample-bharadwaj
Version: 0.0.1
Summary: Sample Package
Home-page: https://github.com/bharadwajvyadavalli/addOneSample
Author: Bharadwaj Yadavalli
Author-email: educationyvb@pm.me
License: UNKNOWN
Project-URL: Bug Tracker, https://github.com/bharadwajvyadavalli/addOneSample
Platform: UNKNOWN
Classifier: Programming Language :: Python :: 3
Classifier: License :: OSI Approved :: MIT License
Classifier: Operating System :: OS Independent
Requires-Python: >=3.6
License-File: LICENSE
